skillcorner/__init__.py
skillcorner/client.py
skillcorner/errors.py
skillcorner/pagination.py
skillcorner/params_list.py
skillcorner/config/class_config.py
skillcorner/config/method_config_list.py
skillcorner-2.6.12.dist-info/METADATA
skillcorner-2.6.12.dist-info/WHEEL
skillcorner-2.6.12.dist-info/entry_points.txt
skillcorner-2.6.12.dist-info/licenses/LICENSE.md
skillcorner-2.6.12.dist-info/RECORD
