Metadata-Version: 2.4
Name: skillcorner
Version: 2.6.12
Summary: Python client for interact with SkillCorner API
License-File: LICENSE.md
Requires-Python: <3.14,>=3.10
Requires-Dist: fitrequest~=1.5.2
Requires-Dist: makefun>=1.15.6
Requires-Dist: orjson>=3.9.10
Requires-Dist: progress>=1.6
